odoo/addons/product_priority/README.rst
odoo/addons/product_priority/__init__.py
odoo/addons/product_priority/__manifest__.py
odoo/addons/product_priority/i18n/de.po
odoo/addons/product_priority/i18n/es.po
odoo/addons/product_priority/i18n/fr.po
odoo/addons/product_priority/i18n/hr.po
odoo/addons/product_priority/i18n/nl_NL.po
odoo/addons/product_priority/i18n/sl.po
odoo/addons/product_priority/models/__init__.py
odoo/addons/product_priority/models/product.py
odoo/addons/product_priority/static/description/icon.png
odoo/addons/product_priority/views/product_view.xml
odoo11_addon_product_priority-11.0.1.1.0.dist-info/DESCRIPTION.rst
odoo11_addon_product_priority-11.0.1.1.0.dist-info/METADATA
odoo11_addon_product_priority-11.0.1.1.0.dist-info/RECORD
odoo11_addon_product_priority-11.0.1.1.0.dist-info/WHEEL
odoo11_addon_product_priority-11.0.1.1.0.dist-info/metadata.json
odoo11_addon_product_priority-11.0.1.1.0.dist-info/top_level.txt
